COPYING
Makefile
qt
setup.py
splay_mod.m4
splay_mod.py
splayperftest.py
test-splay_mod
this-pylint
splay_mod.egg-info/PKG-INFO
splay_mod.egg-info/SOURCES.txt
splay_mod.egg-info/dependency_links.txt
splay_mod.egg-info/top_level.txt