Metadata-Version: 1.1
Name: splay-mod
Version: 1.12
Summary: Pure Python splay tree nodule
Home-page: http://stromberg.dnsalias.org/~strombrg/splay-tree
Author: Daniel Richard Stromberg
Author-email: strombrg@gmail.com
License: Apache v2
Keywords: Splay tree,dictionary-like,sorted dictionary,cache
Platform: Cross platform
Classifier: Development Status :: 5 - Production/Stable
Classifier: Intended Audience :: Developers
Classifier: Programming Language :: Python :: 2
Classifier: Programming Language :: Python :: 3
